README.md
setup.py
OnePy/__init__.py
OnePy/config.py
OnePy/constants.py
OnePy/environment.py
OnePy/event.py
OnePy/main.py
OnePy/builtin_module/__init__.py
OnePy/builtin_module/data_readers/__init__.py
OnePy/builtin_module/data_readers/csvreader.py
OnePy/builtin_module/data_readers/mongodb_reader.py
OnePy/builtin_module/mongodb_saver/__init__.py
OnePy/builtin_module/mongodb_saver/csv_saver.py
OnePy/builtin_module/mongodb_saver/mongodb_config.py
OnePy/builtin_module/mongodb_saver/tushare_saver.py
OnePy/builtin_module/plotters/__init__.py
OnePy/builtin_module/plotters/by_plotly.py
OnePy/builtin_module/recorders/__init__.py
OnePy/builtin_module/recorders/stock_recorder.py
OnePy/builtin_module/recorders/stock_recorder_series.py
OnePy/builtin_module/trade_log/__init__.py
OnePy/builtin_module/trade_log/base_log.py
OnePy/builtin_module/trade_log/match_engine.py
OnePy/builtin_module/trade_log/stock_log.py
OnePy/custom_module/__init__.py
OnePy/custom_module/cleaner_sma.py
OnePy/sys_module/__init__.py
OnePy/sys_module/base_broker.py
OnePy/sys_module/base_cleaner.py
OnePy/sys_module/base_reader.py
OnePy/sys_module/base_recorder.py
OnePy/sys_module/base_riskmanager.py
OnePy/sys_module/base_strategy.py
OnePy/sys_module/metabase_env.py
OnePy/sys_module/components/__init__.py
OnePy/sys_module/components/cash_checker.py
OnePy/sys_module/components/exceptions.py
OnePy/sys_module/components/logger.py
OnePy/sys_module/components/market_maker.py
OnePy/sys_module/components/order_checker.py
OnePy/sys_module/components/order_generator.py
OnePy/sys_module/components/output.py
OnePy/sys_module/components/signal_generator.py
OnePy/sys_module/models/__init__.py
OnePy/sys_module/models/bar_backtest.py
OnePy/sys_module/models/base_bar.py
OnePy/sys_module/models/base_series.py
OnePy/sys_module/models/signals.py
OnePy/sys_module/models/orders/__init__.py
OnePy/sys_module/models/orders/base_order.py
OnePy/sys_module/models/orders/general_order.py
OnePy/utils/__init__.py
Onepy_trader.egg-info/PKG-INFO
Onepy_trader.egg-info/SOURCES.txt
Onepy_trader.egg-info/dependency_links.txt
Onepy_trader.egg-info/requires.txt
Onepy_trader.egg-info/top_level.txt