Metadata-Version: 1.0
Name: Onepy-trader
Version: 2.1
Summary: Python Backtesting library for OnePiece.
Home-page: https://github.com/Chandlercjy/OnePy
Author: Chandler_Chan
Author-email: chenjiayicjy@gmail.com
License: MIT
Platform: UNKNOWN
